quickstart/__init__.py
quickstart/quickstart_blobs_async.py
quickstart/quickstart_blobs_sync.py
txpy/__init__.py
txpy/azurehelper/__init__.py
txpy/azurehelper/storage/__init__.py
txpy/azurehelper/storage/blobs_async.py
txpy/azurehelper/storage/blobs_sync.py
txpy/azurehelper/storage/images_utils.py
txpy_azurehelper-0.1.1.dist-info/LICENSE
txpy_azurehelper-0.1.1.dist-info/METADATA
txpy_azurehelper-0.1.1.dist-info/WHEEL
txpy_azurehelper-0.1.1.dist-info/top_level.txt
txpy_azurehelper-0.1.1.dist-info/RECORD
