Metadata-Version: 2.1
Name: txpy-azurehelper
Version: 0.1.1
Summary: A wrapper around the Azure SDK for Python
Home-page: https://github.com/tyxio/txpy-azurehelper
Author: Philippe Huet
Author-email: philhu@tyxio.com
License: MIT License
Platform: UNKNOWN
Requires-Dist: azure-core (>=1.3.0)
Requires-Dist: azure-storage-blob (>=12.3.0)
Requires-Dist: aiohttp
